Metadata-Version: 2.1
Name: tkkit
Version: 1.0.0
Summary: Write tkinter (Windows/Mac GUI) interface faster and easier
Author: bigeyex
Author-email: bigeyex@gmail.com
License: UNKNOWN
Platform: UNKNOWN
License-File: LICENSE
